netunicorn/py.typed
netunicorn/base/__init__.py
netunicorn/base/architecture.py
netunicorn/base/deployment.py
netunicorn/base/environment_definitions.py
netunicorn/base/execution_graph.py
netunicorn/base/experiment.py
netunicorn/base/nodes.py
netunicorn/base/pipeline.py
netunicorn/base/task.py
netunicorn/base/types.py
netunicorn/base/utils.py
netunicorn/director/base/__init__.py
netunicorn/director/base/resources.py
netunicorn/director/base/types.py
netunicorn/director/base/utils.py
netunicorn/director/base/connectors/__init__.py
netunicorn/director/base/connectors/protocol.py
netunicorn/director/base/connectors/types.py
netunicorn_base-0.4.1.dist-info/METADATA
netunicorn_base-0.4.1.dist-info/WHEEL
netunicorn_base-0.4.1.dist-info/top_level.txt
netunicorn_base-0.4.1.dist-info/RECORD
