Metadata-Version: 2.1
Name: netunicorn-base
Version: 0.4.1
Summary: netunicorn base module
Author-email: Roman Beltiukov <rbeltiukov@ucsb.edu>
License: MIT
Keywords: netunicorn
Classifier: Programming Language :: Python :: 3
Classifier: Programming Language :: Python :: 3.9
Classifier: Programming Language :: Python :: 3.10
Classifier: Programming Language :: Python :: 3.11
Classifier: Programming Language :: Python :: 3.12
Classifier: Programming Language :: Python :: 3.13
Requires-Python: >=3.9
Requires-Dist: returns >=0.20.0
Requires-Dist: typing-extensions
Requires-Dist: pydantic >=2.0.0
Requires-Dist: networkx
